ml_library/ActivationFunctions.py
ml_library/CostFunctions.py
ml_library/DecisionTree.py
ml_library/LinearClassifier.py
ml_library/LinearRegression.py
ml_library/MLP.py
ml_library/MLPOptimizers.py
ml_library/NonLinearRegression.py
ml_library/Optimizers.py
ml_library/SVMDual.py
ml_library/SVMPrimal.py
ml_library/__init__.py
ml_library-1.0.dist-info/LICENCE.txt
ml_library-1.0.dist-info/METADATA
ml_library-1.0.dist-info/WHEEL
ml_library-1.0.dist-info/top_level.txt
ml_library-1.0.dist-info/RECORD
