Metadata-Version: 2.1
Name: ml_library
Version: 1.0
Summary: Machine learning algorithms for regression and classification
Home-page: 
Author: Souhayla Touk
Author-email: souhayla.tawk11@gmail.com
License: MIT
Classifier: Development Status :: 5 - Production/Stable
Classifier: Intended Audience :: Education
Classifier: Operating System :: Microsoft :: Windows
Classifier: License :: OSI Approved :: MIT License
Classifier: Programming Language :: Python :: 3
License-File: LICENCE.txt
Requires-Dist: Numpy
